dbS3/__init__.py
dbS3/data_operations.py
dbS3/s3_storage.py
dbS3-0.1.6.dist-info/METADATA
dbS3-0.1.6.dist-info/WHEEL
dbS3-0.1.6.dist-info/top_level.txt
dbS3-0.1.6.dist-info/RECORD
