Metadata-Version: 2.1
Name: dbS3
Version: 0.1.6
Summary: Pequeno banco de dados que armazena informações no S3 usando TinyDB.
Home-page: https://github.com/wandersomMv/dbS3
Author: Wanderson Viana
Author-email: wanderson.viana@minervafoods.com
Classifier: Programming Language :: Python :: 3
Classifier: License :: OSI Approved :: MIT License
Classifier: Operating System :: OS Independent
Requires-Python: >=3.8
Requires-Dist: boto3 ==1.28.25
Requires-Dist: tinydb ==4.8.0
